[
    {
        "href": "/latest-news",
        "title": "最新资讯"
    },
    {
        "href": "/blog",
        "title": "博客集合"
    },
    {
        "href": "/bast-practices",
        "title": "最佳实践"
    },
    {
        "href": "/questions",
        "title": "问题集合"
    },
    {
        "href": "/base",
        "title": "前端基础"
    },
    {
        "href": "/frame",
        "title": "前端框架"
    },
    {
        "href": "/server",
        "title": "工程化"
    },
    {
        "href": "/server",
        "title": "性能优化"
    },
    {
        "href": "/server",
        "title": "服务端"
    },
    {
        "href": "/server",
        "title": "浏览器"
    },
    {
        "href": "/server",
        "title": "部署运维"
    }
]
